{
  "update_url": "https://clients2.google.com/service/update2/crx",
  "manifest_version": 2,
  "name": "Toucan",
  "description": "Learn a new language just by browsing the internet.",
  "version": "0.1.25",
  "icons": {
    "16": "icon16.png",
    "48": "icon48.png",
    "128": "icon128.png"
  },
  "permissions": [
    "storage",
    "cookies",
    "http://localhost:3000/*",
    "https://jointoucan.com/*",
    "https://*.jointoucan.com/*",
    "https://*.ngrok.io/*",
    "https://*.google.com/*",
    "https://*.youtube.com/*",
    "https://*.amazon.com/*",
    "https://*.yahoo.com/*",
    "https://*.facebook.com/*",
    "https://*.reddit.com/*",
    "https://*.wikipedia.org/*",
    "https://*.ebay.com/*",
    "https://*.bing.com/*",
    "https://*.netflix.com/*",
    "https://*.force.com/*",
    "https://*.office.com/*",
    "https://*.live.com/*",
    "https://*.espn.com/*",
    "https://*.chase.com/*",
    "https://*.tmall.com/*",
    "https://*.twitter.com/*",
    "https://*.instagram.com/*",
    "https://*.twitch.tv/*",
    "https://*.linkedin.com/*",
    "https://*.dropbox.com/*",
    "https://*.microsoftonline.com/*",
    "https://*.cnn.com/*",
    "https://*.microsoft.com/*",
    "https://*.salesforce.com/*",
    "https://*.apple.com/*",
    "https://*.craigslist.org/*",
    "https://*.pornhub.com/*",
    "https://*.walmart.com/*",
    "https://*.myshopify.com/*",
    "https://*.sohu.com/*",
    "https://*.nytimes.com/*",
    "https://*.qq.com/*",
    "https://*.imdb.com/*",
    "https://*.adobe.com/*",
    "https://*.instructure.com/*",
    "https://*.livejasmin.com/*",
    "https://*.stackoverflow.com/*",
    "https://*.login.tmall.com/*",
    "https://*.zillow.com/*",
    "https://*.indeed.com/*",
    "https://*.imgur.com/*",
    "https://*.wellsfargo.com/*",
    "https://*.spotify.com/*",
    "https://*.taobao.com/*",
    "https://*.yelp.com/*",
    "https://*.msn.com/*",
    "https://*.amazonaws.com/*",
    "https://*.jd.com/*",
    "https://*.paypal.com/*",
    "https://*.baidu.com/*",
    "https://*.360.cn/*",
    "https://*.tumblr.com/*",
    "https://*.etsy.com/*",
    "https://*.hulu.com/*",
    "https://*.fandom.com/*",
    "https://*.pinterest.com/*",
    "https://*.wordpress.com/*",
    "https://*.soundcloud.com/*",
    "https://*.weather.com/*",
    "https://*.foxnews.com/*",
    "https://*.capitalone.com/*",
    "https://*.stackexchange.com/*",
    "https://*.blogspot.com/*",
    "https://*.intuit.com/*",
    "https://*.xvideos.com/*",
    "https://*.bbc.com/*",
    "https://*.pages.tmall.com/*",
    "https://*.washingtonpost.com/*",
    "https://*.okta.com/*",
    "https://*.bestbuy.com/*",
    "https://*.sina.com.cn/*",
    "https://*.github.com/*",
    "https://*.xfinity.com/*",
    "https://*.cnet.com/*",
    "https://*.nih.gov/*",
    "https://*.weibo.com/*",
    "https://*.homedepot.com/*",
    "https://*.medium.com/*",
    "https://*.breitbart.com/*",
    "https://*.americanexpress.com/*",
    "https://*.usps.com/*",
    "https://*.businessinsider.com/*",
    "https://*.theguardian.com/*",
    "https://*.wikihow.com/*",
    "https://*.zendesk.com/*",
    "https://*.canva.com/*",
    "https://*.forbes.com/*",
    "https://*.airbnb.com/*",
    "https://*.discordapp.com/*",
    "https://*.target.com/*",
    "https://*.patch.com/*",
    "https://*.booking.com/*",
    "https://*.citi.com/*",
    "https://*.office365.com/*",
    "https://*.tripadvisor.com/*",
    "https://*.bankofamerica.com/*",
    "https://*.gfycat.com/*",
    "https://*.glassdoor.com/*",
    "https://*.ups.com/*",
    "https://*.fiverr.com/*",
    "https://*.aliexpress.com/*",
    "https://*.godaddy.com/*",
    "https://*.roblox.com/*",
    "https://*.thepiratebay.org/*",
    "https://*.vimeo.com/*",
    "https://*.zoom.us/*",
    "https://*.fedex.com/*",
    "https://*.realtor.com/*",
    "https://*.aol.com/*",
    "https://*.slickdeals.net/*",
    "https://*.amazon.co.uk/*",
    "https://*.cnbc.com/*",
    "https://*.eventbrite.com/*",
    "https://*.usatoday.com/*",
    "https://*.vice.com/*",
    "https://*.xhamster.com/*",
    "https://*.adp.com/*",
    "https://*.t.co/*",
    "https://*.att.com/*",
    "https://*.trello.com/*",
    "https://*.ca.gov/*",
    "https://*.bbc.co.uk/*",
    "https://*.go.com/*",
    "https://*.pandora.com/*",
    "https://*.heavy.com/*",
    "https://*.duckduckgo.com/*",
    "https://*.thesaurus.com/*",
    "https://*.quizlet.com/*",
    "https://*.fidelity.com/*",
    "https://*.healthline.com/*",
    "https://*.wsj.com/*",
    "https://*.cbssports.com/*",
    "https://*.nypost.com/*",
    "https://*.nfl.com/*",
    "https://*.xnxx.com/*",
    "https://*.expedia.com/*",
    "https://*.box.com/*",
    "https://*.amazon.co.jp/*",
    "https://*.yahoo.co.jp/*",
    "https://*.csdn.net/*",
    "https://*.mlb.com/*",
    "https://*.wayfair.com/*",
    "https://*.redd.it/*",
    "https://*.chaturbate.com/*",
    "https://*.w3schools.com/*",
    "https://*.google.com.hk/*",
    "https://*.onlinesbi.com/*",
    "https://*.drudgereport.com/*",
    "https://*.costco.com/*",
    "https://*.dailymail.co.uk/*",
    "https://*.shutterstock.com/*",
    "https://*.huffpost.com/*",
    "https://*.archive.org/*",
    "https://*.goodreads.com/*",
    "https://*.lowes.com/*",
    "https://*.macys.com/*",
    "https://*.squarespace.com/*",
    "https://*.taboola.com/*",
    "https://*.babytree.com/*",
    "https://*.alipay.com/*",
    "https://*.southwest.com/*",
    "https://*.google.com.tw/*",
    "https://*.slack.com/*",
    "https://*.discover.com/*",
    "https://*.noaa.gov/*",
    "https://*.grammarly.com/*",
    "https://*.buzzfeed.com/*",
    "https://*.khanacademy.org/*",
    "https://*.verizonwireless.com/*",
    "https://*.blackboard.com/*",
    "https://*.alibaba.com/*",
    "https://*.google.com.sg/*",
    "https://*.weebly.com/*",
    "https://*.gamepedia.com/*",
    "https://*.creditkarma.com/*",
    "https://*.bloomberg.com/*",
    "https://*.marriott.com/*",
    "https://*.shopify.com/*",
    "https://*.delta.com/*",
    "https://*.wix.com/*",
    "https://*.rakuten.com/*",
    "https://*.webmd.com/*",
    "https://*.creditonebank.com/*",
    "https://*.upwork.com/*",
    "https://*.udemy.com/*",
    "https://*.groupon.com/*",
    "https://*.brobible.com/*",
    "https://*.aa.com/*",
    "https://*.deviantart.com/*",
    "https://*.marketwatch.com/*",
    "https://*.usbank.com/*",
    "https://*.surveymonkey.com/*",
    "https://*.nbcnews.com/*",
    "https://*.tianya.cn/*",
    "https://*.ticketmaster.com/*",
    "https://*.giphy.com/*",
    "https://*.spankbang.com/*",
    "https://*.theepochtimes.com/*",
    "https://*.teacherspayteachers.com/*",
    "https://*.wunderground.com/*",
    "https://*.whatsapp.com/*",
    "https://*.kayak.com/*",
    "https://*.npr.org/*",
    "https://*.xinhuanet.com/*",
    "https://*.newegg.com/*",
    "https://*.evernote.com/*",
    "https://*.kohls.com/*",
    "https://*.hootsuite.com/*",
    "https://*.bleacherreport.com/*",
    "https://*.list-manage.com/*",
    "https://*.irs.gov/*",
    "https://*.ikea.com/*",
    "https://*.accuweather.com/*",
    "https://*.trulia.com/*",
    "https://*.ask.com/*",
    "https://*.sex.com/*",
    "https://*.cbsnews.com/*",
    "https://*.patreon.com/*",
    "https://*.unsplash.com/*",
    "https://*.usaa.com/*",
    "https://*.constantcontact.com/*",
    "https://*.united.com/*",
    "https://*.vk.com/*",
    "https://*.youporn.com/*",
    "https://*.quora.com/*",
    "https://*.mailchimp.com/*",
    "https://*.meetup.com/*",
    "https://*.messenger.com/*",
    "https://*.verizon.com/*",
    "https://*.myworkday.com/*",
    "https://*.usnews.com/*",
    "https://*.redfin.com/*",
    "https://*.spectrum.net/*",
    "https://*.mozilla.org/*",
    "https://*.gamespot.com/*",
    "https://*.steamcommunity.com/*",
    "https://*.lotterypost.com/*",
    "https://*.westernjournal.com/*",
    "https://*.wowhead.com/*",
    "https://*.hotels.com/*",
    "https://*.pnc.com/*",
    "https://*.genius.com/*",
    "https://*.ign.com/*",
    "https://*.t-mobile.com/*",
    "https://*.crunchyroll.com/*",
    "https://*.fantasypros.com/*",
    "https://*.gap.com/*",
    "https://*.audible.com/*",
    "https://*.dell.com/*",
    "https://*.bhphotovideo.com/*",
    "https://*.rottentomatoes.com/*",
    "https://*.steampowered.com/*",
    "https://*.dailycaller.com/*",
    "https://*.people.com/*",
    "https://*.nbcsports.com/*",
    "https://*.pixabay.com/*",
    "https://*.merriam-webster.com/*",
    "https://*.kickstarter.com/*",
    "https://*.ancestry.com/*",
    "https://*.chron.com/*",
    "https://*.taleo.net/*",
    "https://*.concursolutions.com/*",
    "https://*.outbrain.com/*",
    "https://*.oracle.com/*",
    "https://*.weather.gov/*",
    "https://*.wikimedia.org/*",
    "https://*.att.net/*",
    "https://*.autotrader.com/*",
    "https://*.ziprecruiter.com/*",
    "https://*.speedtest.net/*",
    "https://*.gizmodo.com/*",
    "https://*.nike.com/*",
    "https://*.reuters.com/*",
    "https://*.okezone.com/*",
    "https://*.gotomeeting.com/*",
    "https://*.cloudfront.net/*",
    "https://*.schwab.com/*",
    "https://*.sfgate.com/*",
    "https://*.skype.com/*",
    "https://*.battle.net/*",
    "https://*.dailymotion.com/*",
    "https://*.ed.gov/*",
    "https://*.qualtrics.com/*",
    "https://*.cargurus.com/*",
    "https://*.investopedia.com/*",
    "https://*.netteller.com/*",
    "https://*.reverb.com/*",
    "https://*.hubspot.com/*",
    "https://*.urbandictionary.com/*",
    "https://*.celebrityinsider.org/*",
    "https://*.allrecipes.com/*",
    "https://*.wetransfer.com/*",
    "https://*.slideshare.net/*",
    "https://*.nextdoor.com/*",
    "https://*.hp.com/*",
    "https://*.coinloan.io/*",
    "https://*.thedailybeast.com/*",
    "https://*.nordstrom.com/*",
    "https://*.rarbg.to/*",
    "https://*.whitepages.com/*",
    "https://*.ny.gov/*",
    "https://*.mit.edu/*",
    "https://*.norton.com/*",
    "https://*.abcnews.go.com/*",
    "https://*.atlassian.net/*",
    "https://*.collegeboard.org/*",
    "https://*.biblegateway.com/*",
    "https://*.walgreens.com/*",
    "https://*.poshmark.com/*",
    "https://*.hilton.com/*",
    "https://*.theverge.com/*",
    "https://*.chegg.com/*",
    "https://*.ladbible.com/*",
    "https://*.cars.com/*",
    "https://*.thehill.com/*",
    "https://*.dictionary.com/*",
    "https://*.politico.com/*",
    "https://*.overstock.com/*",
    "https://*.smugmug.com/*",
    "https://*.webex.com/*",
    "https://*.nesn.com/*",
    "https://*.adoptapet.com/*",
    "https://*.priceline.com/*",
    "https://*.world.tmall.com/*",
    "https://*.asana.com/*",
    "https://*.tmz.com/*",
    "https://*.blizzard.com/*",
    "https://*.myworkdayjobs.com/*",
    "https://*.staples.com/*",
    "https://*.sprint.com/*",
    "https://*.247sports.com/*",
    "https://*.schoology.com/*",
    "https://*.uscis.gov/*",
    "https://*.cengage.com/*",
    "https://*.cbslocal.com/*",
    "https://*.op.gg/*",
    "https://*.barnesandnoble.com/*",
    "https://*.lifewire.com/*",
    "https://*.epwk.com/*",
    "https://*.vistaprint.com/*",
    "https://*.vagaro.com/*",
    "https://*.twimg.com/*",
    "https://*.icloud.com/*",
    "https://*.samsclub.com/*",
    "https://*.samsung.com/*",
    "https://*.shutterfly.com/*",
    "https://*.houzz.com/*",
    "https://*.pinimg.com/*",
    "https://*.apartments.com/*",
    "https://*.syf.com/*",
    "https://*.kbb.com/*",
    "https://*.istockphoto.com/*",
    "https://*.blogger.com/*",
    "https://*.redtube.com/*",
    "https://*.4chan.org/*",
    "https://*.adultfriendfinder.com/*",
    "https://*.feedly.com/*",
    "https://*.okcupid.com/*",
    "https://*.vrbo.com/*",
    "https://*.tradingview.com/*",
    "https://*.bedbathandbeyond.com/*",
    "https://*.mheducation.com/*",
    "https://*.pcmag.com/*",
    "https://*.pexels.com/*",
    "https://*.foodnetwork.com/*",
    "https://*.disney.go.com/*",
    "https://*.zappos.com/*",
    "https://*.edmunds.com/*",
    "https://*.touristtube.com/*",
    "https://*.pornhublive.com/*",
    "https://*.pof.com/*",
    "https://*.spanishdict.com/*",
    "https://*.envato.com/*",
    "https://*.icims.com/*",
    "https://*.time.com/*",
    "https://*.netsuite.com/*",
    "https://*.lifehacker.com/*",
    "https://*.ameritrade.com/*",
    "https://*.harvard.edu/*",
    "https://*.zqktzsj.com/*",
    "https://*.mediafire.com/*",
    "https://*.docusign.net/*",
    "https://*.jpmorganchase.com/*",
    "https://*.ultimate-guitar.com/*",
    "https://*.cvs.com/*",
    "https://*.match.com/*",
    "https://*.latimes.com/*",
    "https://*.ultipro.com/*",
    "https://*.sephora.com/*",
    "https://*.mayoclinic.org/*",
    "https://*.manyvids.com/*",
    "https://*.panda.tv/*",
    "https://*.telegram.org/*",
    "https://*.service-now.com/*",
    "https://*.engadget.com/*",
    "https://*.starbucks.com/*",
    "https://*.mapquest.com/*",
    "https://*.tdbank.com/*",
    "https://*.squareup.com/*",
    "https://*.timeanddate.com/*",
    "https://*.vox.com/*",
    "https://*.retailmenot.com/*",
    "https://*.motor1.com/*",
    "https://*.zoho.com/*",
    "https://*.zhanqi.tv/*",
    "https://*.myfreecams.com/*",
    "https://*.apnews.com/*",
    "https://*.intentmedia.net/*",
    "https://*.researchgate.net/*",
    "https://*.sportbible.com/*",
    "https://*.mashable.com/*",
    "https://*.thefreedictionary.com/*",
    "https://*.cbs.com/*",
    "https://*.files.wordpress.com/*",
    "https://*.ibanking-services.com/*",
    "https://*.doordash.com/*",
    "https://*.flickr.com/*",
    "https://*.custhelp.com/*",
    "https://*.teachable.com/*",
    "https://*.detail.tmall.com/*",
    "https://*.duolingo.com/*",
    "https://*.worldstarhiphop.com/*",
    "https://*.iheart.com/*",
    "https://*.joinhoney.com/*",
    "https://*.inc.com/*",
    "https://*.swagbucks.com/*",
    "https://*.myfitnesspal.com/*",
    "https://*.wired.com/*",
    "https://*.secureinternetbank.com/*",
    "https://*.scribd.com/*",
    "https://*.rei.com/*",
    "https://*.china.com.cn/*",
    "https://*.gofundme.com/*",
    "https://*.td.com/*",
    "https://*.wixsite.com/*",
    "https://*.legacy.com/*",
    "https://*.sourceforge.net/*",
    "https://*.stubhub.com/*",
    "https://*.kaiserpermanente.org/*",
    "https://*.ea.com/*",
    "https://*.uber.com/*",
    "https://*.zerohedge.com/*",
    "https://*.offerup.com/*",
    "https://*.pch.com/*",
    "https://*.pbs.org/*",
    "https://*.synchronycredit.com/*",
    "https://*.freepik.com/*",
    "https://*.infusionsoft.com/*",
    "https://*.xbox.com/*",
    "https://*.narvar.com/*",
    "https://*.suntrust.com/*",
    "https://*.ecollege.com/*",
    "https://*.digitaltrends.com/*",
    "https://*.churchofjesuschrist.org/*",
    "https://*.state.gov/*",
    "https://*.study.com/*",
    "https://*.carsforsale.com/*",
    "https://*.theatlantic.com/*",
    "https://*.caijing.com.cn/*",
    "https://*.howtogeek.com/*",
    "https://*.carfax.com/*",
    "https://*.ecosia.org/*",
    "https://*.jcpenney.com/*",
    "https://*.officedepot.com/*",
    "https://*.smartsheet.com/*",
    "https://*.grubhub.com/*",
    "https://*.techradar.com/*",
    "https://*.beeg.com/*",
    "https://*.medicalnewstoday.com/*",
    "https://*.woot.com/*",
    "https://*.ksl.com/*",
    "https://*.psychologytoday.com/*",
    "https://*.astrologyanswers.com/*",
    "https://*.geico.com/*",
    "https://*.behance.net/*",
    "https://*.searchdimension.com/*",
    "https://*.kissanime.ru/*",
    "https://*.quasa.io/*",
    "https://*.onelogin.com/*",
    "https://*.directv.com/*",
    "https://*.zulily.com/*",
    "https://*.emojipedia.org/*",
    "https://*.monster.com/*",
    "https://*.gotowebinar.com/*",
    "https://*.1337x.to/*",
    "https://*.dbbp1.net/*",
    "https://*.dickssportinggoods.com/*",
    "https://*.cox.net/*",
    "https://*.yandex.ru/*",
    "https://*.telegraph.co.uk/*",
    "https://*.nba.com/*",
    "https://*.minecraft.net/*",
    "https://*.adidas.com/*",
    "https://*.bizrate.com/*"
  ],
  "optional_permissions": [
    "*://*/*"
  ],
  "background": {
    "scripts": [
      "static/js/background.js"
    ],
    "persistent": true
  },
  "chrome_url_overrides": {
    "newtab": "index.html"
  },
  "content_security_policy": "script-src 'self' https://cdn.segment.com https://cdn.amplitude.com https://www.google-analytics.com https://code.jquery.com/jquery-3.3.1.slim.min.js https://cdnjs.cloudflare.com/ajax/libs/popper.js/1.14.7/umd/popper.min.js https://stackpath.bootstrapcdn.com/bootstrap/4.3.1/js/bootstrap.min.js; object-src 'self'; connect-src ws://localhost:9090/ https://toucanapi.com/graphql https://stage.toucanapi.com/graphql http://localhost:4000/graphql https://api.segment.io/v1/batch https://sentry.io; report-to https://sentry.io/api/1859254/security/?sentry_key=09a91674818e4578badec84327b88a97",
  "browser_action": {
    "default_icon": "images/Icon28.png",
    "default_popup": "popup.html"
  },
  "web_accessible_resources": [
    "images/disabledIcon38.png",
    "releaseToggles.json",
    "images/logo-color-sm.svg",
    "images/logo-color-horizontal.svg",
    "images/close.svg",
    "fonts/*.woff2",
    "images/toucan.png"
  ]
}